discord_markdown/__init__.py
discord_markdown/ast.py
discord_markdown/compiler.py
discord_markdown/discord_markdown.py
discord_markdown/lexer.py
discord_markdown/parser.py
discord_markdown/spec.py
discord_markdown-0.4.0.dist-info/WHEEL
discord_markdown-0.4.0.dist-info/METADATA
discord_markdown-0.4.0.dist-info/RECORD
