Metadata-Version: 2.1
Name: discord-markdown
Version: 0.4.0
Summary: Convert discord messages to HTML
Home-page: https://github.com/bitjockey42/discord-markdown
License: MIT
Author: BitJockey
Author-email: bitjockey@jackpoint.network
Requires-Python: >=3.6,<4.0
Classifier: License :: OSI Approved :: MIT License
Classifier: Programming Language :: Python :: 3
Classifier: Programming Language :: Python :: 3.6
Classifier: Programming Language :: Python :: 3.7
Classifier: Programming Language :: Python :: 3.8
Project-URL: Repository, https://github.com/bitjockey42/discord-markdown
